{
  "annotations": {
    "list": [
      {
        "builtIn": 1,
        "datasource": {
          "type": "datasource",
          "uid": "grafana"
        },
        "enable": true,
        "hide": true,
        "iconColor": "rgba(0, 211, 255, 1)",
        "name": "Annotations & Alerts",
        "type": "dashboard"
      }
    ]
  },
  "editable": true,
  "fiscalYearStartMonth": 0,
  "graphTooltip": 0,
  "id": 95,
  "links": [],
  "liveNow": false,
  "panels": [
    {
      "collapsed": true,
      "datasource": {
        "type": "datasource",
        "uid": "grafana"
      },
      "gridPos": {
        "h": 1,
        "w": 24,
        "x": 0,
        "y": 0
      },
      "id": 31,
      "panels": [
        {
          "datasource": {
            "uid": "${postgresql}"
          },
          "fieldConfig": {
            "defaults": {
              "color": {
                "mode": "thresholds"
              },
              "custom": {
                "align": "auto",
                "cellOptions": {
                  "type": "color-text"
                },
                "filterable": true
              },
              "mappings": [
                {
                  "options": {
                    "ERROR": {
                      "color": "dark-orange",
                      "index": 2,
                      "text": "ERROR"
                    },
                    "FATAL": {
                      "color": "dark-red",
                      "index": 3,
                      "text": "FATAL"
                    },
                    "INFO": {
                      "color": "blue",
                      "index": 0,
                      "text": "INFO"
                    },
                    "WARNING": {
                      "color": "yellow",
                      "index": 1,
                      "text": "WARNING"
                    }
                  },
                  "type": "value"
                }
              ],
              "thresholds": {
                "mode": "absolute",
                "steps": [
                  {
                    "color": "yellow"
                  }
                ]
              }
            },
            "overrides": [
              {
                "matcher": {
                  "id": "byName",
                  "options": "message"
                },
                "properties": [
                  {
                    "id": "custom.width",
                    "value": 1533
                  }
                ]
              },
              {
                "matcher": {
                  "id": "byName",
                  "options": "severity"
                },
                "properties": [
                  {
                    "id": "custom.width",
                    "value": 94
                  },
                  {
                    "id": "custom.cellOptions",
                    "value": {
                      "mode": "basic",
                      "type": "color-background"
                    }
                  },
                  {
                    "id": "custom.width",
                    "value": 1
                  }
                ]
              },
              {
                "matcher": {
                  "id": "byName",
                  "options": "application_name"
                },
                "properties": [
                  {
                    "id": "custom.width",
                    "value": 219
                  }
                ]
              },
              {
                "matcher": {
                  "id": "byName",
                  "options": "host_name"
                },
                "properties": [
                  {
                    "id": "custom.width",
                    "value": 217
                  }
                ]
              },
              {
                "matcher": {
                  "id": "byName",
                  "options": "time"
                },
                "properties": [
                  {
                    "id": "custom.width",
                    "value": 213
                  }
                ]
              },
              {
                "matcher": {
                  "id": "byName",
                  "options": "issue_name"
                },
                "properties": [
                  {
                    "id": "custom.width",
                    "value": 188
                  }
                ]
              },
              {
                "matcher": {
                  "id": "byName",
                  "options": "i"
                },
                "properties": [
                  {
                    "id": "custom.width",
                    "value": 25
                  }
                ]
              }
            ]
          },
          "gridPos": {
            "h": 17,
            "w": 24,
            "x": 0,
            "y": 1
          },
          "id": 29,
          "options": {
            "showHeader": true,
            "sortBy": []
          },
          "pluginVersion": "8.0.7",
          "targets": [
            {
              "datasource": {
                "uid": "${postgresql}"
              },
              "format": "table",
              "group": [],
              "metricColumn": "none",
              "rawQuery": true,
              "rawSql": "SELECT severity,time,application_name,message,issue_name,host_name\nFROM public.\"ErrorReports\"\nWHERE partition='${partition}' AND time >= ${__from} AND time <= ${__to}\nORDER BY -time\n",
              "refId": "A",
              "select": [
                [
                  {
                    "params": [
                      "chain"
                    ],
                    "type": "column"
                  }
                ]
              ],
              "table": "\"ErrorReports\"",
              "timeColumn": "\"time\"",
              "timeColumnType": "int8",
              "where": [
                {
                  "name": "$__unixEpochFilter",
                  "params": [],
                  "type": "macro"
                }
              ]
            }
          ],
          "title": "Message Reporting",
          "transformations": [],
          "type": "table"
        }
      ],
      "targets": [
        {
          "datasource": {
            "type": "datasource",
            "uid": "grafana"
          },
          "refId": "A"
        }
      ],
      "title": "Logs",
      "type": "row"
    },
    {
      "collapsed": false,
      "datasource": {
        "type": "datasource",
        "uid": "grafana"
      },
      "gridPos": {
        "h": 1,
        "w": 24,
        "x": 0,
        "y": 1
      },
      "id": 12,
      "panels": [],
      "targets": [
        {
          "datasource": {
            "type": "datasource",
            "uid": "grafana"
          },
          "refId": "A"
        }
      ],
      "title": "Generic Info",
      "type": "row"
    },
    {
      "datasource": {
        "uid": "${influxdb}"
      },
      "description": "Displays timestamp data.\n\nThe left axis indicates the current timestamp value in seconds from the UNIX epoch. The actual timestamp value is 62,500,000 times this number.\n\nThe right axis indicates the average change between two successive timestamps over one minute. This should be 62,500,000 from the 62.5MHz frequency.",
      "fieldConfig": {
        "defaults": {
          "color": {
            "mode": "palette-classic"
          },
          "custom": {
            "axisBorderShow": false,
            "axisCenteredZero": false,
            "axisColorMode": "text",
            "axisLabel": "Timestamp/UNIX seconds",
            "axisPlacement": "auto",
            "barAlignment": 0,
            "drawStyle": "line",
            "fillOpacity": 0,
            "gradientMode": "none",
            "hideFrom": {
              "legend": false,
              "tooltip": false,
              "viz": false
            },
            "insertNulls": false,
            "lineInterpolation": "linear",
            "lineWidth": 1,
            "pointSize": 5,
            "scaleDistribution": {
              "type": "linear"
            },
            "showPoints": "auto",
            "spanNulls": false,
            "stacking": {
              "group": "A",
              "mode": "none"
            },
            "thresholdsStyle": {
              "mode": "off"
            }
          },
          "mappings": [],
          "thresholds": {
            "mode": "absolute",
            "steps": [
              {
                "color": "green",
                "value": null
              },
              {
                "color": "red",
                "value": 80
              }
            ]
          },
          "unit": "none"
        },
        "overrides": [
          {
            "matcher": {
              "id": "byFrameRefID",
              "options": "B"
            },
            "properties": [
              {
                "id": "custom.axisPlacement",
                "value": "right"
              },
              {
                "id": "custom.axisLabel",
                "value": "Mean Δ timestamp over 1 minute"
              },
              {
                "id": "unit"
              },
              {
                "id": "custom.axisSoftMin",
                "value": 0
              },
              {
                "id": "custom.axisSoftMax",
                "value": 125000000
              }
            ]
          }
        ]
      },
      "gridPos": {
        "h": 18,
        "w": 12,
        "x": 0,
        "y": 2
      },
      "id": 20,
      "options": {
        "legend": {
          "calcs": [],
          "displayMode": "list",
          "placement": "bottom",
          "showLegend": true
        },
        "tooltip": {
          "mode": "single",
          "sort": "none"
        }
      },
      "targets": [
        {
          "alias": "Timestamp ([[tag_partition_id]])",
          "datasource": {
            "uid": "${influxdb}"
          },
          "groupBy": [
            {
              "params": [
                "partition_id"
              ],
              "type": "tag"
            }
          ],
          "hide": false,
          "measurement": "dunedaq.timing.timingfirmwareinfo.MasterMonitorData",
          "orderByTime": "ASC",
          "policy": "default",
          "query": "SELECT \"timestamp\" / 62500000 AS \"Timestamp\" FROM \"dunedaq.timing.timingfirmwareinfo.MasterMonitorData\" WHERE (\"partition_id\" =~ /^$partition$/) AND $timeFilter GROUP BY \"partition_id\"",
          "rawQuery": true,
          "refId": "A",
          "resultFormat": "time_series",
          "select": [
            [
              {
                "params": [
                  "timestamp"
                ],
                "type": "field"
              },
              {
                "params": [
                  "/ 62500000"
                ],
                "type": "math"
              },
              {
                "params": [
                  "Timestamp"
                ],
                "type": "alias"
              }
            ]
          ],
          "tags": [
            {
              "key": "partition_id",
              "operator": "=~",
              "value": "/^$partition$/"
            }
          ]
        },
        {
          "alias": "Δ timestamp ([[tag_partition_id]])",
          "datasource": {
            "uid": "${influxdb}"
          },
          "groupBy": [
            {
              "params": [
                "1m"
              ],
              "type": "time"
            },
            {
              "params": [
                "partition_id"
              ],
              "type": "tag"
            }
          ],
          "hide": false,
          "measurement": "dunedaq.timing.timingfirmwareinfo.MasterMonitorData",
          "orderByTime": "ASC",
          "policy": "default",
          "query": "SELECT derivative(mean(\"timestamp\"), 1s) AS \"Timestamp change\" FROM \"dunedaq.timing.timingfirmwareinfo.MasterMonitorData\" WHERE (\"partition_id\" =~ /^$partition$/) AND time >= now() - 3h - 1m and time <= now() GROUP BY time(1m), \"partition_id\"",
          "rawQuery": false,
          "refId": "B",
          "resultFormat": "time_series",
          "select": [
            [
              {
                "params": [
                  "timestamp"
                ],
                "type": "field"
              },
              {
                "params": [],
                "type": "mean"
              },
              {
                "params": [
                  "1s"
                ],
                "type": "derivative"
              },
              {
                "params": [
                  "Timestamp change"
                ],
                "type": "alias"
              }
            ]
          ],
          "tags": [
            {
              "key": "partition_id",
              "operator": "=~",
              "value": "/^$partition$/"
            }
          ]
        }
      ],
      "title": "Timestamp",
      "type": "timeseries"
    },
    {
      "datasource": {
        "uid": "${influxdb}"
      },
      "description": "Displays the status of the MMCM and PLL over time.\n\nNote the PLL is expected to be \"Bad\" unless an upstream device is connected.",
      "fieldConfig": {
        "defaults": {
          "color": {
            "mode": "thresholds"
          },
          "custom": {
            "fillOpacity": 70,
            "hideFrom": {
              "legend": false,
              "tooltip": false,
              "viz": false
            },
            "insertNulls": false,
            "lineWidth": 0,
            "spanNulls": false
          },
          "mappings": [
            {
              "options": {
                "match": "true",
                "result": {
                  "color": "semi-dark-green",
                  "index": 0,
                  "text": "Good"
                }
              },
              "type": "special"
            },
            {
              "options": {
                "match": "false",
                "result": {
                  "color": "semi-dark-red",
                  "index": 1,
                  "text": "Bad"
                }
              },
              "type": "special"
            }
          ],
          "thresholds": {
            "mode": "absolute",
            "steps": [
              {
                "color": "green",
                "value": null
              }
            ]
          }
        },
        "overrides": []
      },
      "gridPos": {
        "h": 11,
        "w": 12,
        "x": 12,
        "y": 2
      },
      "id": 6,
      "interval": "10s",
      "options": {
        "alignValue": "left",
        "legend": {
          "displayMode": "list",
          "placement": "bottom",
          "showLegend": false
        },
        "mergeValues": true,
        "rowHeight": 0.9,
        "showValue": "auto",
        "tooltip": {
          "mode": "none",
          "sort": "none"
        }
      },
      "targets": [
        {
          "datasource": {
            "uid": "${influxdb}"
          },
          "groupBy": [
            {
              "params": [
                "$__interval"
              ],
              "type": "time"
            },
            {
              "params": [
                "null"
              ],
              "type": "fill"
            }
          ],
          "measurement": "dunedaq.timing.timinghardwareinfo.TimingPC059MonitorData",
          "orderByTime": "ASC",
          "policy": "default",
          "query": "SELECT min(\"mmcm_ok\") AS \"MMCM OK\", min(\"pll_ok\") AS \"PLL Locked\" FROM \"dunedaq.timing.timinghardwareinfo.TimingPC059MonitorData\" WHERE (\"partition_id\" =~ /^$partition$/) AND $timeFilter GROUP BY time($__interval) fill(null)",
          "rawQuery": false,
          "refId": "A",
          "resultFormat": "logs",
          "select": [
            [
              {
                "params": [
                  "mmcm_ok"
                ],
                "type": "field"
              },
              {
                "params": [],
                "type": "min"
              },
              {
                "params": [
                  "MMCM OK"
                ],
                "type": "alias"
              }
            ],
            [
              {
                "params": [
                  "pll_ok"
                ],
                "type": "field"
              },
              {
                "params": [],
                "type": "min"
              },
              {
                "params": [
                  "PLL Locked"
                ],
                "type": "alias"
              }
            ]
          ],
          "tags": [
            {
              "key": "partition_id",
              "operator": "=~",
              "value": "/^$partition$/"
            }
          ]
        },
        {
          "datasource": {
            "uid": "${influxdb}"
          },
          "hide": true,
          "query": "SELECT\n  min(\"mmcm_sticky\") AS \"Previous Fault in MMCM\",\n  min(\"pll_sticky\") AS \"Previous error in PLL\"\nFROM \"dunedaq.timing.timinghardwareinfo.TimingTLUMonitorData\",\"dunedaq.timing.timinghardwareinfo.TimingPC059MonitorData\",\"dunedaq.timing.timinghardwareinfo.TimingMIBMonitorData\",\"dunedaq.timing.timinghardwareinfo.TimingFIBMonitorData\" WHERE (\"partition_id\" = '${partition}') AND $timeFilter GROUP BY time($__interval) fill(null)",
          "rawQuery": true,
          "refId": "B"
        }
      ],
      "title": "Master information",
      "transparent": true,
      "type": "state-timeline"
    },
    {
      "datasource": {
        "uid": "${influxdb}"
      },
      "description": "Displays the \"pll_sticky\" flag: This goes low if the device has a PLL (Phase-Locked Loop) fault, and remains low until the next reset.\n\nCurrently expected to always be low, since this flag will be set as low after the reset before the PLL becomes ready.",
      "fieldConfig": {
        "defaults": {
          "color": {
            "mode": "fixed"
          },
          "mappings": [
            {
              "options": {
                "match": "false",
                "result": {
                  "color": "semi-dark-red",
                  "index": 0,
                  "text": "Fault occurred in PLL since last reset"
                }
              },
              "type": "special"
            },
            {
              "options": {
                "match": "true",
                "result": {
                  "color": "semi-dark-green",
                  "index": 1,
                  "text": "No faults in PLL since last reset"
                }
              },
              "type": "special"
            }
          ],
          "noValue": "PLL not in use",
          "thresholds": {
            "mode": "absolute",
            "steps": [
              {
                "color": "rgb(127, 127, 127)",
                "value": null
              }
            ]
          }
        },
        "overrides": []
      },
      "gridPos": {
        "h": 7,
        "w": 5,
        "x": 13,
        "y": 13
      },
      "id": 26,
      "options": {
        "colorMode": "background",
        "graphMode": "area",
        "justifyMode": "auto",
        "orientation": "auto",
        "reduceOptions": {
          "calcs": [
            "lastNotNull"
          ],
          "fields": "",
          "values": false
        },
        "text": {},
        "textMode": "auto",
        "wideLayout": true
      },
      "pluginVersion": "10.2.2",
      "targets": [
        {
          "datasource": {
            "uid": "${influxdb}"
          },
          "groupBy": [],
          "measurement": "dunedaq.timing.timinghardwareinfo.TimingPC059MonitorData",
          "orderByTime": "ASC",
          "policy": "default",
          "query": "SELECT \"pll_sticky\" FROM \"dunedaq.timing.timinghardwareinfo.TimingTLUMonitorData\",\"dunedaq.timing.timinghardwareinfo.TimingPC059MonitorData\",\"dunedaq.timing.timinghardwareinfo.TimingFIBMonitorData\" WHERE (\"partition_id\" = '${partition}') AND $timeFilter",
          "rawQuery": true,
          "refId": "A",
          "resultFormat": "time_series",
          "select": [
            [
              {
                "params": [
                  "pll_sticky"
                ],
                "type": "field"
              }
            ]
          ],
          "tags": []
        }
      ],
      "title": "PLL faults",
      "type": "stat"
    },
    {
      "datasource": {
        "uid": "${influxdb}"
      },
      "description": "Displays the \"mmcm_sticky\" flag. This flag will go low if a fault is detected in the MMCM (Mixed-Mode Clock Manager), and remain low until the device is reset.\n\nCurrently expected to always be low, since this flag will be set as low after the reset before the MMCM becomes ready.",
      "fieldConfig": {
        "defaults": {
          "color": {
            "mode": "thresholds"
          },
          "mappings": [
            {
              "options": {
                "match": "false",
                "result": {
                  "color": "semi-dark-red",
                  "index": 0,
                  "text": "Fault occurred in MMCM since last reset"
                }
              },
              "type": "special"
            },
            {
              "options": {
                "match": "true",
                "result": {
                  "color": "semi-dark-green",
                  "index": 1,
                  "text": "No faults in MMCM since last reset"
                }
              },
              "type": "special"
            }
          ],
          "noValue": "MMCM not in use",
          "thresholds": {
            "mode": "absolute",
            "steps": [
              {
                "color": "rgb(128, 128, 128)",
                "value": null
              }
            ]
          }
        },
        "overrides": []
      },
      "gridPos": {
        "h": 7,
        "w": 5,
        "x": 18,
        "y": 13
      },
      "id": 27,
      "options": {
        "colorMode": "background",
        "graphMode": "area",
        "justifyMode": "auto",
        "orientation": "auto",
        "reduceOptions": {
          "calcs": [
            "lastNotNull"
          ],
          "fields": "",
          "values": false
        },
        "text": {},
        "textMode": "auto",
        "wideLayout": true
      },
      "pluginVersion": "10.2.2",
      "targets": [
        {
          "datasource": {
            "uid": "${influxdb}"
          },
          "groupBy": [],
          "measurement": "dunedaq.timing.timinghardwareinfo.TimingPC059MonitorData",
          "orderByTime": "ASC",
          "policy": "default",
          "query": "SELECT \"mmcm_sticky\" FROM \"dunedaq.timing.timinghardwareinfo.TimingTLUMonitorData\",\"dunedaq.timing.timinghardwareinfo.TimingPC059MonitorData\",\"dunedaq.timing.timinghardwareinfo.TimingMIBMonitorData\",\"dunedaq.timing.timinghardwareinfo.TimingFIBMonitorData\" WHERE (\"partition_id\" = '${partition}') AND $timeFilter",
          "rawQuery": true,
          "refId": "A",
          "resultFormat": "time_series",
          "select": [
            [
              {
                "params": [
                  "pll_sticky"
                ],
                "type": "field"
              }
            ]
          ],
          "tags": []
        }
      ],
      "title": "MMCM faults",
      "type": "stat"
    },
    {
      "datasource": {
        "uid": "${influxdb}"
      },
      "description": "Counts of commands in the TMC.\n - Reset commands: Number of requests sent to reset the master.\n - Status commands: Number of requests sent to get the status of the master.\n - Timestamp set commands: Number of requests sent to set the timestamp in the master device.\n - Delay set commands: Number of requests sent to set the delay of a connected endpoint device.\n - Generic commands: Number of commands requests (i.e. echo).",
      "fieldConfig": {
        "defaults": {
          "color": {
            "mode": "thresholds"
          },
          "mappings": [],
          "thresholds": {
            "mode": "absolute",
            "steps": [
              {
                "color": "semi-dark-purple",
                "value": null
              }
            ]
          }
        },
        "overrides": []
      },
      "gridPos": {
        "h": 12,
        "w": 12,
        "x": 0,
        "y": 20
      },
      "id": 22,
      "options": {
        "displayMode": "basic",
        "minVizHeight": 10,
        "minVizWidth": 0,
        "namePlacement": "auto",
        "orientation": "horizontal",
        "reduceOptions": {
          "calcs": [
            "lastNotNull"
          ],
          "fields": "",
          "values": false
        },
        "showUnfilled": true,
        "text": {},
        "valueMode": "color"
      },
      "pluginVersion": "10.2.2",
      "targets": [
        {
          "datasource": {
            "uid": "${influxdb}"
          },
          "groupBy": [],
          "measurement": "dunedaq.timinglibs.timingmastercontrollerinfo.Info",
          "orderByTime": "ASC",
          "policy": "default",
          "refId": "A",
          "resultFormat": "logs",
          "select": [
            [
              {
                "params": [
                  "sent_master_io_reset_cmds"
                ],
                "type": "field"
              },
              {
                "params": [
                  "Reset requests"
                ],
                "type": "alias"
              }
            ],
            [
              {
                "params": [
                  "sent_master_print_status_cmds"
                ],
                "type": "field"
              },
              {
                "params": [
                  "Status requests"
                ],
                "type": "alias"
              }
            ],
            [
              {
                "params": [
                  "sent_master_set_timestamp_cmds"
                ],
                "type": "field"
              },
              {
                "params": [
                  "Timestamp set requests"
                ],
                "type": "alias"
              }
            ],
            [
              {
                "params": [
                  "sent_master_set_endpoint_delay_cmds"
                ],
                "type": "field"
              },
              {
                "params": [
                  "Delay set requests"
                ],
                "type": "alias"
              }
            ],
            [
              {
                "params": [
                  "sent_master_send_fl_command_cmds"
                ],
                "type": "field"
              },
              {
                "params": [
                  "Command requests"
                ],
                "type": "alias"
              }
            ]
          ],
          "tags": [
            {
              "key": "partition_id",
              "operator": "=~",
              "value": "/^$partition$/"
            }
          ]
        }
      ],
      "title": "Timing Master Controller command counts",
      "type": "bargauge"
    },
    {
      "datasource": {
        "uid": "${influxdb}"
      },
      "description": "Counts of commands in the THI.\n - Received commands: Number of command requests received by the THI.\n - Accepted commands: Number of commands received by THI which are recognised.\n - Rejected commands: Number of commands received by THI which are not recognised.\n - Failed commands: Number of commands accepted by THI which fail in execution.",
      "fieldConfig": {
        "defaults": {
          "color": {
            "mode": "palette-classic"
          },
          "mappings": [],
          "thresholds": {
            "mode": "absolute",
            "steps": [
              {
                "color": "green",
                "value": null
              }
            ]
          }
        },
        "overrides": []
      },
      "gridPos": {
        "h": 12,
        "w": 12,
        "x": 12,
        "y": 20
      },
      "id": 24,
      "options": {
        "displayMode": "basic",
        "minVizHeight": 10,
        "minVizWidth": 0,
        "namePlacement": "auto",
        "orientation": "horizontal",
        "reduceOptions": {
          "calcs": [
            "lastNotNull"
          ],
          "fields": "",
          "values": false
        },
        "showUnfilled": true,
        "text": {},
        "valueMode": "color"
      },
      "pluginVersion": "10.2.2",
      "targets": [
        {
          "datasource": {
            "uid": "${influxdb}"
          },
          "groupBy": [],
          "measurement": "dunedaq.timinglibs.timinghardwaremanagerpdiinfo.Info",
          "orderByTime": "ASC",
          "policy": "default",
          "refId": "A",
          "resultFormat": "logs",
          "select": [
            [
              {
                "params": [
                  "received_hw_commands_counter"
                ],
                "type": "field"
              },
              {
                "params": [
                  "Recieved commands"
                ],
                "type": "alias"
              }
            ],
            [
              {
                "params": [
                  "accepted_hw_commands_counter"
                ],
                "type": "field"
              },
              {
                "params": [
                  "Accepted commands"
                ],
                "type": "alias"
              }
            ],
            [
              {
                "params": [
                  "rejected_hw_commands_counter"
                ],
                "type": "field"
              },
              {
                "params": [
                  "Rejected commands"
                ],
                "type": "alias"
              }
            ],
            [
              {
                "params": [
                  "failed_hw_commands_counter"
                ],
                "type": "field"
              },
              {
                "params": [
                  "Failed commands"
                ],
                "type": "alias"
              }
            ]
          ],
          "tags": [
            {
              "key": "partition_id",
              "operator": "=~",
              "value": "/^$partition$/"
            }
          ]
        }
      ],
      "title": "Timing Hardware Interface command counts",
      "type": "bargauge"
    },
    {
      "collapsed": true,
      "datasource": {
        "type": "datasource",
        "uid": "grafana"
      },
      "gridPos": {
        "h": 1,
        "w": 24,
        "x": 0,
        "y": 32
      },
      "id": 8,
      "panels": [
        {
          "datasource": {
            "uid": "${influxdb}"
          },
          "description": "Only active is the master is a pc059 board.\n\nIndicates which mux (0-7) is selected.",
          "fieldConfig": {
            "defaults": {
              "color": {
                "mode": "thresholds"
              },
              "mappings": [],
              "thresholds": {
                "mode": "absolute",
                "steps": [
                  {
                    "color": "semi-dark-yellow"
                  }
                ]
              }
            },
            "overrides": []
          },
          "gridPos": {
            "h": 7,
            "w": 3,
            "x": 0,
            "y": 32
          },
          "id": 14,
          "options": {
            "colorMode": "value",
            "graphMode": "area",
            "justifyMode": "auto",
            "orientation": "auto",
            "reduceOptions": {
              "calcs": [
                "lastNotNull"
              ],
              "fields": "/^dunedaq\\.timing.timinghardwareinfo.TimingPC059MonitorData.active_sfp_mux$/",
              "values": false
            },
            "text": {},
            "textMode": "auto"
          },
          "pluginVersion": "8.0.7",
          "targets": [
            {
              "datasource": {
                "uid": "${influxdb}"
              },
              "groupBy": [],
              "measurement": "dunedaq.timing.timinghardwareinfo.TimingPC059MonitorData",
              "orderByTime": "ASC",
              "policy": "default",
              "query": "SELECT \"sfp_flt\" FROM \"dunedaq.timing.timinghardwareinfo.TimingTLUMonitorData\" WHERE $timeFilter",
              "rawQuery": false,
              "refId": "A",
              "resultFormat": "time_series",
              "select": [
                [
                  {
                    "params": [
                      "active_sfp_mux"
                    ],
                    "type": "field"
                  }
                ]
              ],
              "tags": [
                {
                  "key": "partition_id",
                  "operator": "=~",
                  "value": "/^$partition$/"
                }
              ]
            }
          ],
          "title": "PC059 Active mux",
          "type": "stat"
        },
        {
          "datasource": {
            "uid": "${influxdb}"
          },
          "description": "Only active if the master is a pc059 board.\n\nIndicates the SFP statuses of the upstream and downstream SFPs.\n\nNote LOS (Loss Of Signal) is expected to be \"Bad\" if no SFP is connected.",
          "fieldConfig": {
            "defaults": {
              "color": {
                "mode": "thresholds"
              },
              "custom": {
                "fillOpacity": 70,
                "lineWidth": 0
              },
              "mappings": [
                {
                  "options": {
                    "0": {
                      "color": "semi-dark-green",
                      "index": 3,
                      "text": "Good"
                    },
                    "1": {
                      "color": "semi-dark-red",
                      "index": 2,
                      "text": "Bad"
                    }
                  },
                  "type": "value"
                },
                {
                  "options": {
                    "match": "false",
                    "result": {
                      "color": "semi-dark-green",
                      "index": 0,
                      "text": "Good"
                    }
                  },
                  "type": "special"
                },
                {
                  "options": {
                    "match": "true",
                    "result": {
                      "color": "semi-dark-red",
                      "index": 1,
                      "text": "Bad"
                    }
                  },
                  "type": "special"
                }
              ],
              "thresholds": {
                "mode": "absolute",
                "steps": [
                  {
                    "color": "green"
                  }
                ]
              }
            },
            "overrides": []
          },
          "gridPos": {
            "h": 12,
            "w": 21,
            "x": 3,
            "y": 32
          },
          "id": 10,
          "interval": "10s",
          "options": {
            "alignValue": "left",
            "legend": {
              "displayMode": "list",
              "placement": "bottom",
              "showLegend": false
            },
            "mergeValues": true,
            "rowHeight": 0.9,
            "showValue": "auto",
            "tooltip": {
              "mode": "single"
            }
          },
          "targets": [
            {
              "datasource": {
                "uid": "${influxdb}"
              },
              "groupBy": [],
              "measurement": "dunedaq.timing.timinghardwareinfo.TimingPC059MonitorData",
              "orderByTime": "ASC",
              "policy": "default",
              "query": "SELECT\n  min(\"usfp_los\") AS \"Upstream SFP LOS\",\n  min(\"usfp_flt\") AS \"Upstream SFP fault\",\n  (min(\"sfp_los\")&1) AS \"SFP 0 LOS\",\n  (min(\"sfp_los\")&2)/2 AS \"SFP 1 LOS\",\n  (min(\"sfp_los\")&4)/4 AS \"SFP 2 LOS\",\n  (min(\"sfp_los\")&8)/8 AS \"SFP 3 LOS\",\n  (min(\"sfp_los\")&16)/16 AS \"SFP 4 LOS\",\n  (min(\"sfp_los\")&32)/32 AS \"SFP 5 LOS\",\n  (min(\"sfp_los\")&64)/64 AS \"SFP 6 LOS\",\n  (min(\"sfp_los\")&128)/128 AS \"SFP 7 LOS\"\nFROM \"dunedaq.timing.timinghardwareinfo.TimingPC059MonitorData\" WHERE (\"partition_id\" = '${partition}') AND $timeFilter GROUP BY time($__interval) fill(null)",
              "rawQuery": true,
              "refId": "A",
              "resultFormat": "logs",
              "select": [
                [
                  {
                    "params": [
                      "usfp_los"
                    ],
                    "type": "field"
                  },
                  {
                    "params": [
                      "Upstream SFP LOS"
                    ],
                    "type": "alias"
                  }
                ]
              ],
              "tags": []
            }
          ],
          "title": "PC059 data",
          "type": "state-timeline"
        },
        {
          "datasource": {
            "uid": "${influxdb}"
          },
          "description": "Only active is the master is a TLU.\n\nIndicates the status of the SFP of a TLU device.",
          "fieldConfig": {
            "defaults": {
              "color": {
                "mode": "thresholds"
              },
              "custom": {
                "fillOpacity": 70,
                "lineWidth": 0
              },
              "mappings": [
                {
                  "options": {
                    "match": "true",
                    "result": {
                      "color": "semi-dark-red",
                      "index": 0,
                      "text": "Bad"
                    }
                  },
                  "type": "special"
                },
                {
                  "options": {
                    "match": "false",
                    "result": {
                      "color": "semi-dark-green",
                      "index": 1,
                      "text": "Good"
                    }
                  },
                  "type": "special"
                }
              ],
              "thresholds": {
                "mode": "absolute",
                "steps": [
                  {
                    "color": "green"
                  },
                  {
                    "color": "red",
                    "value": 80
                  }
                ]
              }
            },
            "overrides": []
          },
          "gridPos": {
            "h": 12,
            "w": 24,
            "x": 0,
            "y": 44
          },
          "id": 16,
          "options": {
            "alignValue": "left",
            "legend": {
              "displayMode": "list",
              "placement": "bottom",
              "showLegend": false
            },
            "mergeValues": true,
            "rowHeight": 0.9,
            "showValue": "auto",
            "tooltip": {
              "mode": "single"
            }
          },
          "targets": [
            {
              "datasource": {
                "uid": "${influxdb}"
              },
              "groupBy": [],
              "measurement": "dunedaq.timing.timinghardwareinfo.TimingPC059MonitorData",
              "orderByTime": "ASC",
              "policy": "default",
              "query": "SELECT min(\"sfp_flt\") AS \"SFP Fault\" FROM \"dunedaq.timing.timinghardwareinfo.TimingTLUMonitorData\" WHERE (\"partition_id\" = '${partition}') AND $timeFilter GROUP BY time($__interval) fill(null)",
              "rawQuery": true,
              "refId": "A",
              "resultFormat": "logs",
              "select": [
                [
                  {
                    "params": [
                      "sfp_los"
                    ],
                    "type": "field"
                  },
                  {
                    "params": [
                      "alias"
                    ],
                    "type": "alias"
                  }
                ]
              ],
              "tags": []
            }
          ],
          "title": "TLU data",
          "type": "state-timeline"
        },
        {
          "datasource": {
            "uid": "${influxdb}"
          },
          "description": "Only active if the master is a MIB.\n\nIndicates the statuses of the SFPs on the MIB.\n\nNote LOS (Loss Of Signal) is expected to be \"Bad\" if there is not SFP attached.",
          "fieldConfig": {
            "defaults": {
              "color": {
                "mode": "thresholds"
              },
              "custom": {
                "fillOpacity": 70,
                "lineWidth": 0
              },
              "mappings": [
                {
                  "options": {
                    "match": "true",
                    "result": {
                      "color": "semi-dark-green",
                      "index": 0,
                      "text": "Good"
                    }
                  },
                  "type": "special"
                },
                {
                  "options": {
                    "match": "false",
                    "result": {
                      "color": "semi-dark-red",
                      "index": 1,
                      "text": "Bad"
                    }
                  },
                  "type": "special"
                }
              ],
              "thresholds": {
                "mode": "absolute",
                "steps": [
                  {
                    "color": "green"
                  },
                  {
                    "color": "red",
                    "value": 80
                  }
                ]
              }
            },
            "overrides": []
          },
          "gridPos": {
            "h": 12,
            "w": 24,
            "x": 0,
            "y": 56
          },
          "id": 18,
          "options": {
            "alignValue": "left",
            "legend": {
              "displayMode": "list",
              "placement": "bottom",
              "showLegend": false
            },
            "mergeValues": true,
            "rowHeight": 0.9,
            "showValue": "auto",
            "tooltip": {
              "mode": "single"
            }
          },
          "targets": [
            {
              "datasource": {
                "uid": "${influxdb}"
              },
              "groupBy": [],
              "measurement": "dunedaq.timing.timinghardwareinfo.TimingPC059MonitorData",
              "orderByTime": "ASC",
              "policy": "default",
              "query": "SELECT\n  (min(\"sfp_0_flt\") ^ true) AS \"SFP 0 Fault\",\n  (min(\"sfp_0_los\") ^ true) AS \"SFP 0 LOS\",\n  (min(\"sfp_1_flt\") ^ true) AS \"SFP 1 Fault\",\n  (min(\"sfp_1_los\") ^ true) AS \"SFP 1 LOS\",\n  (min(\"sfp_2_flt\") ^ true) AS \"SFP 2 Fault\",\n  (min(\"sfp_2_los\") ^ true) AS \"SFP 2 LOS\"\nFROM \"dunedaq.timing.timinghardwareinfo.TimingPC059MonitorData\" WHERE (\"partition_id\" = '${partition}') AND $timeFilter GROUP BY time($__interval) fill(null)",
              "rawQuery": true,
              "refId": "A",
              "resultFormat": "time_series",
              "select": [
                [
                  {
                    "params": [
                      "sfp_los"
                    ],
                    "type": "field"
                  }
                ]
              ],
              "tags": []
            }
          ],
          "title": "MIB data",
          "type": "state-timeline"
        }
      ],
      "targets": [
        {
          "datasource": {
            "type": "datasource",
            "uid": "grafana"
          },
          "refId": "A"
        }
      ],
      "title": "Expert Info",
      "type": "row"
    }
  ],
  "refresh": "10s",
  "schemaVersion": 38,
  "tags": [
    "v5.0.0",
    "Global"
  ],
  "templating": {
    "list": [
      {
        "current": {
          "selected": false,
          "text": "KluInflux",
          "value": "ffedc550-6555-4a16-a113-aabf2b980c30"
        },
        "hide": 2,
        "includeAll": false,
        "label": "InfluxDB",
        "multi": false,
        "name": "influxdb",
        "options": [],
        "query": "influxdb",
        "refresh": 1,
        "regex": "",
        "skipUrlSync": false,
        "type": "datasource"
      },
      {
        "current": {
          "selected": false,
          "text": "KluPostgreSQL",
          "value": "c7e9e333-25c9-49e7-b209-b9492f70d419"
        },
        "hide": 2,
        "includeAll": false,
        "label": "PostgresSQL",
        "multi": false,
        "name": "postgresql",
        "options": [],
        "query": "postgres",
        "refresh": 1,
        "regex": "",
        "skipUrlSync": false,
        "type": "datasource"
      },
      {
        "current": {
          "selected": false,
          "text": "np02-timing-fanout-2",
          "value": "np02-timing-fanout-2"
        },
        "datasource": {
          "uid": "${influxdb}"
        },
        "definition": "SHOW TAG VALUES FROM \"dunedaq.timinglibs.timinghardwaremanagerpdiinfo.Info\" WITH KEY=\"partition_id\" WHERE $timeFilter",
        "description": "Which timing partition to view",
        "hide": 0,
        "includeAll": false,
        "label": "Partition",
        "multi": false,
        "name": "partition",
        "options": [],
        "query": "SHOW TAG VALUES FROM \"dunedaq.timinglibs.timinghardwaremanagerpdiinfo.Info\" WITH KEY=\"partition_id\" WHERE $timeFilter",
        "refresh": 2,
        "regex": "",
        "skipUrlSync": false,
        "sort": 0,
        "type": "query"
      }
    ]
  },
  "time": {
    "from": "now-24h",
    "to": "now"
  },
  "timepicker": {},
  "timezone": "",
  "title": "Timing",
  "uid": "v5_0_0-timing",
  "version": 2,
  "weekStart": ""
}